shacl_path_query/__init__.py
shacl_path_query/flatten.py
shacl_path_query/model.py
shacl_path_query/parser.py
shacl_path_query_generator-0.1.4.dist-info/licenses/LICENSE
shacl_path_query_generator-0.1.4.dist-info/METADATA
shacl_path_query_generator-0.1.4.dist-info/WHEEL
shacl_path_query_generator-0.1.4.dist-info/top_level.txt
shacl_path_query_generator-0.1.4.dist-info/RECORD
