Metadata-Version: 2.4
Name: shacl-path-query-generator
Version: 0.1.4
Summary: Translate SHACL complex paths into SPARQL CONSTRUCT queries with intermediate variable expansion.
Author-email: Zenon Zacouris <zenon.zacouris@tum.de>
License: MIT
Project-URL: Repository, https://github.com/zenon-z/shacl-path-query-generator
Classifier: License :: OSI Approved :: MIT License
Classifier: Programming Language :: Python :: 3
Classifier: Programming Language :: Python :: 3.9
Classifier: Operating System :: OS Independent
Requires-Python: >=3.9
License-File: LICENSE
Requires-Dist: rdflib==7.1.4
Dynamic: license-file
